menger/__init__.py
menger/analysis/__init__.py
menger/analysis/mengercurvature.py
menger/analysis/visualisation.py
menger/data/MengerCurvature_test_parameters.json
menger/data/README.md
menger/data/__init__.py
menger/data/dummy_data.py
menger/data/files.py
menger/data/mda.txt
menger/data/test_data/tubulin_chain_a.dcd
menger/data/test_data/tubulin_chain_a.pdb
menger/tests/__init__.py
menger/tests/conftest.py
menger/tests/test_menger.py
menger/tests/utils.py
menger/tests/analysis/__init__.py
menger/tests/analysis/test_mengercurvature.py
menger/tests/analysis/test_visualisation.py
menger_curvature-1.1.0.dist-info/licenses/AUTHORS.md
menger_curvature-1.1.0.dist-info/licenses/LICENSE
menger_curvature-1.1.0.dist-info/METADATA
menger_curvature-1.1.0.dist-info/WHEEL
menger_curvature-1.1.0.dist-info/top_level.txt
menger_curvature-1.1.0.dist-info/RECORD
