Metadata-Version: 2.4
Name: menger_curvature
Version: 1.1.0
Summary: This project aims to provide a simple MDAkit for JIT accelerated Menger curvature calculation
Author-email: LBT <reboul@ibpc.fr>
Maintainer-email: LBT <reboul@ibpc.fr>
License:                     GNU GENERAL PUBLIC LICENSE
Project-URL: source, https://github.com/EtienneReboul/menger_curvature
Project-URL: documentation, https://menger-curvature.readthedocs.io
Keywords: molecular simulations
Requires-Python: >=3.9
License-File: LICENSE
License-File: AUTHORS.md
Requires-Dist: MDAnalysis>=2.0.0
Requires-Dist: numba>=0.60.0
Requires-Dist: numpy<=2.1
Requires-Dist: dask
Provides-Extra: test
Requires-Dist: pytest>=6.0; extra == "test"
Requires-Dist: pytest-xdist>=2.5; extra == "test"
Requires-Dist: pytest-cov>=3.0; extra == "test"
Provides-Extra: doc
Requires-Dist: sphinx; extra == "doc"
Requires-Dist: sphinx_rtd_theme; extra == "doc"
Dynamic: license-file
